main.py
setup.py
ASMutation.egg-info/PKG-INFO
ASMutation.egg-info/SOURCES.txt
ASMutation.egg-info/dependency_links.txt
ASMutation.egg-info/requires.txt
ASMutation.egg-info/top_level.txt